i_asana/__init__.py
i_asana/i_asana.py
i_asana-3.0.1.dist-info/LICENSE
i_asana-3.0.1.dist-info/METADATA
i_asana-3.0.1.dist-info/WHEEL
i_asana-3.0.1.dist-info/RECORD
