Metadata-Version: 2.1
Name: i-asana
Version: 3.0.1
Summary: Python interface to Asana
Home-page: https://github.com/aracnid/i-asana
License: MIT
Keywords: python,asana
Author: Jason Romano
Author-email: aracnid@gmail.com
Requires-Python: >=3.10,<4.0
Classifier: License :: OSI Approved :: MIT License
Classifier: Programming Language :: Python :: 3
Classifier: Programming Language :: Python :: 3.10
Classifier: Programming Language :: Python :: 3.11
Classifier: Programming Language :: Python :: 3.12
Requires-Dist: aracnid-logger (>=1.0,<2.0)
Requires-Dist: asana (>=5.0,<6.0)
Requires-Dist: pytz (>=2022.6,<2023.0)
Project-URL: Repository, https://github.com/aracnid/i-asana
